{
  "Items": [
    {
      "key": 1,
      "keyName": "Rage_First",
      "Boss": 3001,
      "PointX": -45,
      "PointY": 0,
      "PointZ": 45
    },
    {
      "key": 2,
      "keyName": "Rage_Sec",
      "Boss": 3001,
      "PointX": -45,
      "PointY": 0,
      "PointZ": -45
    },
    {
      "key": 3,
      "keyName": "Rage_Third",
      "Boss": 3001,
      "PointX": -170,
      "PointY": 0,
      "PointZ": 170
    },
    {
      "key": 4,
      "keyName": "Rage_Final",
      "Boss": 3001,
      "PointX": -420,
      "PointY": 0,
      "PointZ": 10
    }
  ]
}